mcp_http_bridge/__init__.py
mcp_http_bridge/config.py
mcp_http_bridge/main.py
mcp_http_bridge/models.py
mcp_http_bridge/server.py
mcp_http_bridge-1.3.2.dist-info/METADATA
mcp_http_bridge-1.3.2.dist-info/WHEEL
mcp_http_bridge-1.3.2.dist-info/entry_points.txt
mcp_http_bridge-1.3.2.dist-info/RECORD
