Metadata-Version: 2.4
Name: mcp-http-bridge
Version: 1.3.2
Summary: Bridge for stdio-only MCP tools that exposes their stdio protocol via streamable-http
Requires-Python: >=3.12
Requires-Dist: fastmcp>=0.3.0
Requires-Dist: pydantic>=2.0.0
